README.md
setup.cfg
setup.py
github_stargazers/__init__.py
github_stargazers/github.py
github_stargazers/github_stargazers.py
github_stargazers.egg-info/PKG-INFO
github_stargazers.egg-info/SOURCES.txt
github_stargazers.egg-info/dependency_links.txt
github_stargazers.egg-info/entry_points.txt
github_stargazers.egg-info/requires.txt
github_stargazers.egg-info/top_level.txt