Metadata-Version: 1.1
Name: github-stargazers
Version: 0.1.0
Summary: List stargazers and check if a user starred that repository
Home-page: https://github.com/marius92mc/github-stargazers
Author: Marius-Constantin Melemciuc
Author-email: mariuspypi@gmail.com
License: UNKNOWN
Download-URL: https://github.com/marius92mc/github-stargazers/archive/0.1.0.tar.gz
Keywords: command-line,python,github,star,repository,beautifulsoup
Platform: UNKNOWN
